lightem/Clusterer.py
lightem/Embedder.py
lightem/EntityMatcher.py
lightem/Matcher.py
lightem/Table.py
lightem/__init__.py
lightem/version.py
lightem-0.1.7.dist-info/LICENSE
lightem-0.1.7.dist-info/METADATA
lightem-0.1.7.dist-info/WHEEL
lightem-0.1.7.dist-info/top_level.txt
lightem-0.1.7.dist-info/RECORD
